ranksim/__init__.py
ranksim/_base.py
ranksim/_classes.py
ranksim/_filters.py
ranksim/_version.py
ranksim/tests/__init__.py
ranksim/tests/test_common.py
ranksim/tests/test_ranksim.py
rank_similarity-0.0.1.dist-info/LICENSE
rank_similarity-0.0.1.dist-info/METADATA
rank_similarity-0.0.1.dist-info/WHEEL
rank_similarity-0.0.1.dist-info/top_level.txt
rank_similarity-0.0.1.dist-info/zip-safe
rank_similarity-0.0.1.dist-info/RECORD
