Metadata-Version: 2.1
Name: rank-similarity
Version: 0.0.1
Summary: Rank Similarity is a set of non-linear classification and transform tools for large datasets. 
Home-page: https://github.com/KatharineShapcott/rank-similarity
Maintainer: Katharine Shapcott
Maintainer-email: katharine.shapcott@esi-frankfurt.de
License: new BSD
Download-URL: https://github.com/KatharineShapcott/rank-similarity
Platform: UNKNOWN
Classifier: Intended Audience :: Science/Research
Classifier: Intended Audience :: Developers
Classifier: License :: OSI Approved
Classifier: Programming Language :: Python
Classifier: Topic :: Software Development
Classifier: Topic :: Scientific/Engineering
Classifier: Operating System :: Microsoft :: Windows
Classifier: Operating System :: POSIX
Classifier: Operating System :: Unix
Classifier: Operating System :: MacOS
Classifier: Programming Language :: Python :: 3.7
Classifier: Programming Language :: Python :: 3.8
Classifier: Programming Language :: Python :: 3.9
Requires-Dist: scikit-learn (>=0.23)
Requires-Dist: numpy (>=1.14.6)
Requires-Dist: scipy (>=1.1.0)
Provides-Extra: docs
Requires-Dist: sphinx ; extra == 'docs'
Requires-Dist: sphinx-gallery ; extra == 'docs'
Requires-Dist: sphinx-rtd-theme ; extra == 'docs'
Requires-Dist: numpydoc ; extra == 'docs'
Requires-Dist: matplotlib ; extra == 'docs'
Provides-Extra: tests
Requires-Dist: pytest ; extra == 'tests'
